{
  "_format": "hh-sol-cache-2",
  "files": {
    "/Users/michaelchan/Desktop/consensus/contracts/MultiSig.sol": {
      "lastModificationDate": 1656552075570,
      "contentHash": "c1b8f09cd4342b807d40bc6f2f9aed16",
      "sourceName": "contracts/MultiSig.sol",
      "solcConfig": {
        "version": "0.8.13",
        "settings": {
          "optimizer": {
            "enabled": true,
            "runs": 200
          },
          "outputSelection": {
            "*": {
              "*": [
                "abi",
                "evm.bytecode",
                "evm.deployedBytecode",
                "evm.methodIdentifiers",
                "metadata"
              ],
              "": [
                "ast"
              ]
            }
          }
        }
      },
      "imports": [],
      "versionPragmas": [
        "^0.8.13"
      ],
      "artifacts": [
        "MultiSig"
      ]
    },
    "/Users/michaelchan/Desktop/consensus/contracts/TestContract.sol": {
      "lastModificationDate": 1656552840742,
      "contentHash": "d5c4a70ee34c13b79e44f14e1d5c15ca",
      "sourceName": "contracts/TestContract.sol",
      "solcConfig": {
        "version": "0.8.13",
        "settings": {
          "optimizer": {
            "enabled": true,
            "runs": 200
          },
          "outputSelection": {
            "*": {
              "*": [
                "abi",
                "evm.bytecode",
                "evm.deployedBytecode",
                "evm.methodIdentifiers",
                "metadata"
              ],
              "": [
                "ast"
              ]
            }
          }
        }
      },
      "imports": [
        "@openzeppelin/contracts/access/Ownable.sol"
      ],
      "versionPragmas": [
        "^0.8.4"
      ],
      "artifacts": [
        "TestContract"
      ]
    },
    "/Users/michaelchan/Desktop/consensus/node_modules/@openzeppelin/contracts/access/Ownable.sol": {
      "lastModificationDate": 1656434406266,
      "contentHash": "8398972af73b4e9e5ff3b31cad86234f",
      "sourceName": "@openzeppelin/contracts/access/Ownable.sol",
      "solcConfig": {
        "version": "0.8.13",
        "settings": {
          "optimizer": {
            "enabled": true,
            "runs": 200
          },
          "outputSelection": {
            "*": {
              "*": [
                "abi",
                "evm.bytecode",
                "evm.deployedBytecode",
                "evm.methodIdentifiers",
                "metadata"
              ],
              "": [
                "ast"
              ]
            }
          }
        }
      },
      "imports": [
        "../utils/Context.sol"
      ],
      "versionPragmas": [
        "^0.8.0"
      ],
      "artifacts": [
        "Ownable"
      ]
    },
    "/Users/michaelchan/Desktop/consensus/node_modules/@openzeppelin/contracts/utils/Context.sol": {
      "lastModificationDate": 1656434406246,
      "contentHash": "5f2c5c4b6af2dd4551027144797bc8be",
      "sourceName": "@openzeppelin/contracts/utils/Context.sol",
      "solcConfig": {
        "version": "0.8.13",
        "settings": {
          "optimizer": {
            "enabled": true,
            "runs": 200
          },
          "outputSelection": {
            "*": {
              "*": [
                "abi",
                "evm.bytecode",
                "evm.deployedBytecode",
                "evm.methodIdentifiers",
                "metadata"
              ],
              "": [
                "ast"
              ]
            }
          }
        }
      },
      "imports": [],
      "versionPragmas": [
        "^0.8.0"
      ],
      "artifacts": [
        "Context"
      ]
    }
  }
}
